PyScalix/__init__.py
PyScalix/pyscalix.py
PyScalix-0.0.8.dist-info/LICENSE
PyScalix-0.0.8.dist-info/METADATA
PyScalix-0.0.8.dist-info/WHEEL
PyScalix-0.0.8.dist-info/top_level.txt
PyScalix-0.0.8.dist-info/RECORD
