Metadata-Version: 2.1
Name: PyScalix
Version: 0.0.8
Summary: Python Package to convert csv files to SQLite database and SQLite database to csv files
Home-page: https://github.com/husnainkhurshiid/PyScalix.git
Author: Husnain Khurshid
Author-email: muhammadhusnainkh@gmail.com
Keywords: python,PyScalix,csv to sqlite,sqlite to csv,csv,husnain khurshid
Classifier: Development Status :: 1 - Planning
Classifier: Intended Audience :: Developers
Classifier: Programming Language :: Python :: 3
Classifier: Operating System :: Unix
Classifier: Operating System :: MacOS :: MacOS X
Classifier: Operating System :: Microsoft :: Windows
License-File: LICENSE
